bayesmbar/__init__.py
bayesmbar/bayesbar.py
bayesmbar/bayesmbar.py
bayesmbar/cbayesmbar.py
bayesmbar/fastmbar.py
bayesmbar/utils.py
bayesmbar-0.1.1.dist-info/METADATA
bayesmbar-0.1.1.dist-info/WHEEL
bayesmbar-0.1.1.dist-info/licenses/LICENSE
bayesmbar-0.1.1.dist-info/RECORD
