Metadata-Version: 2.4
Name: bayesmbar
Version: 0.1.1
Summary: Bayesian Multistate Bennett Acceptance Ratio (BayesMBAR) methods for free energy calculations.
License-File: LICENSE
Requires-Python: >=3.11
Requires-Dist: blackjax>=1.2.3
Requires-Dist: jax>=0.6.0
Requires-Dist: jaxlib>=0.6.0
Requires-Dist: networkx>=3.3
Requires-Dist: scipy==1.16.0
Requires-Dist: tqdm>=4.66.5
Provides-Extra: testing
Requires-Dist: pytest>=8.3.2; extra == 'testing'
